{
	"IsSplinter": false,
	"IsSensi": false,
	"IsBlister": false,
	"IsBareSkin": false,
	"IsScratch": false,
	"IsSmallCut": false,
	"IsStuckFood": false,
	"IsBackPain": false,
	"IsSoreNeck": false,
	"IsBadDream": false,
	"IsWristTrauma": false,
	"IsShoulderTrauma": false,
	"IsOverconfidence": false,
	"SplinterDuration": 24,
	"SensiDuration": 24,
	"StuckFoodDuration": 2,
	"BlisterDuration": 30,
	"BareSkinDuration": 48,
	"BackPainDuration": 6,
	"SoreNeckDuration": 6,
	"ScratchDuration": 40,
	"SmallCutDuration": 48,
	"WristTraumaDuration": 50,
	"ShoulderTraumaDuration": 60,
	"BadDreamDurationMinutes": 15,
	"IsLogging": false
}