{
	"FireStartingCategory": false,
	"Accelerant": false,
	"Book": false,
	"CardBoardMatches": false,
	"WoodMatches": false,
	"FirstAidCategory": false,
	"HydrogenPeroxide": false,
	"PainKillers": false,
	"ReishiTea": false,
	"RosehipTea": false,
	"WaterTablets": false,
	"FoodCategory": false,
	"BeefJerky": false,
	"CandyBar": false,
	"EnergyBar": false,
	"GranolaBar": false,
	"MRE": false,
	"PeanutButter": false,
	"Crackers": false,
	"Peaches": false,
	"Beans": false,
	"Milk": false,
	"DogFood": false,
	"Sardines": false,
	"TomatoSoup": false,
	"CattailStalk": false,
	"CoffeeCup": false,
	"GreenTeaCup": false,
	"Soda": false,
	"Water": false,
	"ToolCategory": false,
	"Bedroll": false,
	"BearSkinBedroll": false,
	"CanOpener": false,
	"Hatchet": false,
	"LampFuel": false,
	"JerryCan": false,
	"Prybar": false,
	"SewingKit": false,
	"Tools": false,
	"MaterialCategory": false,
	"Cloth": false,
	"Reishi": false,
	"Rosehip": false,
	"ResearchBooks": true,
	"GunsAdvanced": true,
	"HarvestBook": true,
	"GunBook": true,
	"IceFishing": true,
	"FireBook": true,
	"CookingBook": true,
	"Discontinued": true,
	"Peaches_Old": true,
	"Beans_Old": true,
	"MRE_Old": true,
	"Crackers_Old": true,
	"Soda_Old": true,
	"CoffeeTin_Old": true,
	"ResetSettings": false,
	"CatTailTinder": false,
	"SodaOrange": false,
	"GrapeSoda": false,
	"SodaOrange_Old": false,
	"SodaGrape_Old": false
}